simputils/__init__.py
simputils/__version__.py
simputils/algos.py
simputils/caching.py
simputils/dateutils.py
simputils/functional.py
simputils/inspection.py
simputils/logging.py
simputils/math.py
simputils/rnd.py
simputils-0.1.8.dist-info/LICENSE
simputils-0.1.8.dist-info/METADATA
simputils-0.1.8.dist-info/WHEEL
simputils-0.1.8.dist-info/top_level.txt
simputils-0.1.8.dist-info/RECORD
