Metadata-Version: 2.1
Name: simputils
Version: 0.1.8
Home-page: https://github.com/MattiasDC/simputils
Author: Mattias De Charleroy
Author-email: mattias.decharleroy@gmail.com
Platform: any
Requires-Python: >=3.9
License-File: LICENSE
Requires-Dist: aiocache
Requires-Dist: more-itertools
Requires-Dist: rich
Provides-Extra: dev
Requires-Dist: black ; extra == 'dev'
Requires-Dist: flake8 ; extra == 'dev'
Requires-Dist: isort ; extra == 'dev'
Requires-Dist: nox ; extra == 'dev'
Requires-Dist: pre-commit ; extra == 'dev'
Requires-Dist: twine ; extra == 'dev'
Requires-Dist: yamllint ; extra == 'dev'
